Workbook

Sheet Chart of Accounts
A1: CHART OF ACCOUNTS
A3: ACCOUNT NAME | B3: ACCOUNT NUMBER | C3: ACCOUNT TYPE | D3: NORMAL BALANCE
A4: Cash | B4: 101 | C4: Asset | D4: Debit
A5: Accounts Receivable | B5: 110 | C5: Asset | D5: Debit
A6: Office Supplies | B6: 120 | C6: Asset | D6: Debit
A7: Equipment | B7: 150 | C7: Asset | D7: Debit
A8: Account Payable | B8: 201 | C8: Liability | D8: Credit
A9: Owner's Capital | B9: 301 | C9: Equity | D9: Credit
A10: Owner's Drawing | B10: 302 | C10: Equity (Contra) | D10: Debit
A11: Service Revenue | B11: 401 | C11: Revenue | D11: Credit
A12: Rent Expense | B12: 501 | C12: Expense | D12: Debit
A13: Salaries Expense | B13: 510 | C13: Expense | D13: Debit
A14: Utilities Expense | B14: 520 | C14: Expense | D14: Debit

Sheet Journal Entries
A1: Carlo's Digital Solutions
A2: General Journal - July 2026
A4: DATE | B4: ACCOUNT TITLE | C4: REF | D4: DEBIT | E4: CREDIT | F4: NOTES
A5: 46204 | B5: Cash | C5: =VLOOKUP(B5,'Chart of Accounts'!A:B,2,0) -> 101 | D5: 10000 | F5: Owner's Investment
B6: Owner's Capital | C6: =VLOOKUP(B6,'Chart of Accounts'!A:B,2,0) -> 301 | E6: 10000 | F6: Owner's Investment
A7: 46204 | B7: Rent Expense | C7: =VLOOKUP(B7,'Chart of Accounts'!A:B,2,0) -> 501 | D7: 750 | F7: Paid office rent through cash
B8: Cash | C8: =VLOOKUP(B8,'Chart of Accounts'!A:B,2,0) -> 101 | E8: 750 | F8: Paid office rent through cash
A9: 46206 | B9: Office Supplies | C9: =VLOOKUP(B9,'Chart of Accounts'!A:B,2,0) -> 120 | D9: 200 | F9: Purchased office supplies through cash
B10: Cash | C10: =VLOOKUP(B10,'Chart of Accounts'!A:B,2,0) -> 101 | E10: 200 | F10: Purchased office supplies through cash
A11: 46208 | B11: Equipment | C11: =VLOOKUP(B11,'Chart of Accounts'!A:B,2,0) -> 150 | D11: 1500 | F11: Purchased desktop on credit
B12: Account Payable | C12: =VLOOKUP(B12,'Chart of Accounts'!A:B,2,0) -> 201 | E12: 1500 | F12: Purchased desktop on credit
A13: 46211 | B13: Cash | C13: =VLOOKUP(B13,'Chart of Accounts'!A:B,2,0) -> 101 | D13: 3000 | F13: Service Revenue- client paid cash
B14: Service Revenue | C14: =VLOOKUP(B14,'Chart of Accounts'!A:B,2,0) -> 401 | E14: 3000 | F14: Service Revenue- client paid cash
A15: 46215 | B15: Accounts Receivable | C15: =VLOOKUP(B15,'Chart of Accounts'!A:B,2,0) -> 110 | D15: 2200 | F15: Service Revenue-payment to be collected
B16: Service Revenue | C16: =VLOOKUP(B16,'Chart of Accounts'!A:B,2,0) -> 401 | E16: 2200 | F16: Service Revenue-payment to be collected
A17: 46221 | B17: Cash | C17: =VLOOKUP(B17,'Chart of Accounts'!A:B,2,0) -> 101 | D17: 1500 | F17: Collected partial payment from client, service provided on July 12, 2026
B18: Accounts Receivable | C18: =VLOOKUP(B18,'Chart of Accounts'!A:B,2,0) -> 110 | E18: 1500 | F18: Collected partial payment from client, service provided on July 12, 2026
A19: 46223 | B19: Salaries Expense | C19: =VLOOKUP(B19,'Chart of Accounts'!A:B,2,0) -> 510 | D19: 500 | F19: To record salary expense - paid through cash
B20: Cash | C20: =VLOOKUP(B20,'Chart of Accounts'!A:B,2,0) -> 101 | E20: 500 | F20: To record salary expense - paid through cash
A21: 46230 | B21: Utilities Expense | C21: =VLOOKUP(B21,'Chart of Accounts'!A:B,2,0) -> 520 | D21: 180 | F21: To record payment of utilitites through cash
B22: Cash | C22: =VLOOKUP(B22,'Chart of Accounts'!A:B,2,0) -> 101 | E22: 180 | F22: To record payment of utilitites through cash
A23: 46234 | B23: Owner's Drawing | C23: =VLOOKUP(B23,'Chart of Accounts'!A:B,2,0) -> 302 | D23: 800 | F23: Owner's withdrawal
B24: Cash | C24: =VLOOKUP(B24,'Chart of Accounts'!A:B,2,0) -> 101 | E24: 800 | F24: Owner's withdrawal
D25: =SUM(D5:D24) -> 20630 | E25: =SUM(E5:E24) -> 20630
D27: Validation | E27: =IF(D25=E25,"Okay","Please Check") -> Okay

Sheet Trial Balance
A1: Carlo's Digital Solutions
A2: General Journal - July 2026
A3: Trial Balance
A5: ACCOUNT TYPE | B5: ACCOUNT TITLE | C5: REF | D5: DEBIT | E5: CREDIT
A6: ='Chart of Accounts'!C4 -> Asset | B6: ='Chart of Accounts'!A4 -> Cash | C6: =VLOOKUP(B6,'Chart of Accounts'!A:B,2,0) -> 101 | D6: =SUMIFS('Journal Entries'!D:D,'Journal Entries'!B:B,'Trial Balance'!B6)-SUMIFS('Journal Entries'!E:E,'Journal Entries'!B:B,'Trial Balance'!B6) -> 12070
A7: ='Chart of Accounts'!C5 -> Asset | B7: ='Chart of Accounts'!A5 -> Accounts Receivable | C7: =VLOOKUP(B7,'Chart of Accounts'!A:B,2,0) -> 110 | D7: =SUMIFS('Journal Entries'!D:D,'Journal Entries'!B:B,'Trial Balance'!B7)-SUMIFS('Journal Entries'!E:E,'Journal Entries'!B:B,'Trial Balance'!B7) -> 700
A8: ='Chart of Accounts'!C6 -> Asset | B8: ='Chart of Accounts'!A6 -> Office Supplies | C8: =VLOOKUP(B8,'Chart of Accounts'!A:B,2,0) -> 120 | D8: =SUMIFS('Journal Entries'!D:D,'Journal Entries'!B:B,'Trial Balance'!B8)-SUMIFS('Journal Entries'!E:E,'Journal Entries'!B:B,'Trial Balance'!B8) -> 200
A9: ='Chart of Accounts'!C7 -> Asset | B9: ='Chart of Accounts'!A7 -> Equipment | C9: =VLOOKUP(B9,'Chart of Accounts'!A:B,2,0) -> 150 | D9: =SUMIFS('Journal Entries'!D:D,'Journal Entries'!B:B,'Trial Balance'!B9)-SUMIFS('Journal Entries'!E:E,'Journal Entries'!B:B,'Trial Balance'!B9) -> 1500
A10: ='Chart of Accounts'!C8 -> Liability | B10: ='Chart of Accounts'!A8 -> Account Payable | C10: =VLOOKUP(B10,'Chart of Accounts'!A:B,2,0) -> 201 | E10: =SUMIFS('Journal Entries'!E:E,'Journal Entries'!B:B,'Trial Balance'!B10)-SUMIFS('Journal Entries'!D:D,'Journal Entries'!B:B,'Trial Balance'!B10) -> 1500
A11: ='Chart of Accounts'!C9 -> Equity | B11: ='Chart of Accounts'!A9 -> Owner's Capital | C11: =VLOOKUP(B11,'Chart of Accounts'!A:B,2,0) -> 301 | E11: =SUMIFS('Journal Entries'!E:E,'Journal Entries'!B:B,'Trial Balance'!B11)-SUMIFS('Journal Entries'!D:D,'Journal Entries'!B:B,'Trial Balance'!B11) -> 10000
A12: ='Chart of Accounts'!C10 -> Equity (Contra) | B12: ='Chart of Accounts'!A10 -> Owner's Drawing | C12: =VLOOKUP(B12,'Chart of Accounts'!A:B,2,0) -> 302 | D12: =SUMIFS('Journal Entries'!D:D,'Journal Entries'!B:B,'Trial Balance'!B12)-SUMIFS('Journal Entries'!E:E,'Journal Entries'!B:B,'Trial Balance'!B12) -> 800
A13: ='Chart of Accounts'!C11 -> Revenue | B13: ='Chart of Accounts'!A11 -> Service Revenue | C13: =VLOOKUP(B13,'Chart of Accounts'!A:B,2,0) -> 401 | E13: =SUMIFS('Journal Entries'!E:E,'Journal Entries'!B:B,'Trial Balance'!B13)-SUMIFS('Journal Entries'!D:D,'Journal Entries'!B:B,'Trial Balance'!B13) -> 5200
A14: ='Chart of Accounts'!C12 -> Expense | B14: ='Chart of Accounts'!A12 -> Rent Expense | C14: =VLOOKUP(B14,'Chart of Accounts'!A:B,2,0) -> 501 | D14: =SUMIFS('Journal Entries'!D:D,'Journal Entries'!B:B,'Trial Balance'!B14)-SUMIFS('Journal Entries'!E:E,'Journal Entries'!B:B,'Trial Balance'!B14) -> 750
A15: ='Chart of Accounts'!C13 -> Expense | B15: ='Chart of Accounts'!A13 -> Salaries Expense | C15: =VLOOKUP(B15,'Chart of Accounts'!A:B,2,0) -> 510 | D15: =SUMIFS('Journal Entries'!D:D,'Journal Entries'!B:B,'Trial Balance'!B15)-SUMIFS('Journal Entries'!E:E,'Journal Entries'!B:B,'Trial Balance'!B15) -> 500
A16: ='Chart of Accounts'!C14 -> Expense | B16: ='Chart of Accounts'!A14 -> Utilities Expense | C16: =VLOOKUP(B16,'Chart of Accounts'!A:B,2,0) -> 520 | D16: =SUMIFS('Journal Entries'!D:D,'Journal Entries'!B:B,'Trial Balance'!B16)-SUMIFS('Journal Entries'!E:E,'Journal Entries'!B:B,'Trial Balance'!B16) -> 180
D17: =SUM(D6:D16) -> 16700 | E17: =SUM(E6:E16) -> 16700
C19: Validation | D19: =IF(D17=E17,"Okay","Please Check") -> Okay

Sheet Financial Statements
B3: Carlo's Digital Solutions | F3: Carlo's Digital Solutions
B4: Profit & Loss Statement | F4: Balance Sheet
B5: For the month of July 2025 | F5: As of July 31, 2025
B7: Service Revenue | D7: ='Trial Balance'!E13 -> 5200 | F7: Assets
B8: Less: Expenses | F8: Cash | G8: ='Trial Balance'!D6 -> 12070
B9: Rent Expenses | C9: ='Trial Balance'!D14 -> 750 | F9: Accounts Receivable | G9: ='Trial Balance'!D7 -> 700
B10: Salaries Expenses | C10: ='Trial Balance'!D15 -> 500 | F10: Office Supplies | G10: ='Trial Balance'!D8 -> 200
B11: Utilities Expenses | C11: ='Trial Balance'!D16 -> 180 | F11: Equipment | G11: ='Trial Balance'!D9 -> 1500
B12: Total Expenses | D12: =SUM(C9:C11) -> 1430 | F12: Total Assets | G12: =SUM(G8:G11) -> 14470
B13: Net Income | D13: =D7-D12 -> 3770
F14: Liabilities
F15: Accounts Payable | G15: ='Trial Balance'!E10 -> 1500
F16: Total Liabilities
F18: Owner's Equity
F19: Owner's Capital | G19: ='Trial Balance'!E11 -> 10000
F20: Owner's Drawing | G20: ='Trial Balance'!D12*-1 -> -800
F21: Retained Earnings | G21: =D13 -> 3770
F22: Total Owner's Equity | G22: =SUM(G19:G21) -> 12970
F24: Total Liabilities & Equity | G24: =SUM(G15,G22) -> 14470
F27: Validation | G27: =IF(G12=G24,"Okay","Please Check") -> Okay
